utils.cpython-36m-darwin.so
umis/__init__.py
umis/barcodes.py
umis/umis.py
umis-1.0.3.dist-info/DESCRIPTION.rst
umis-1.0.3.dist-info/METADATA
umis-1.0.3.dist-info/RECORD
umis-1.0.3.dist-info/WHEEL
umis-1.0.3.dist-info/entry_points.txt
umis-1.0.3.dist-info/metadata.json
umis-1.0.3.dist-info/top_level.txt
