Metadata-Version: 2.0
Name: umis
Version: 1.0.3
Summary: Package for estimating UMI counts in Transcript Tag Counting data.
Home-page: https://github.com/vals/umis
Author: Valentine Svensson
Author-email: valentine@nxn.se
License: UNKNOWN
Platform: UNKNOWN
Requires-Dist: click
Requires-Dist: pysam (>=0.8.3)
Requires-Dist: pandas
Requires-Dist: regex
Requires-Dist: scipy
Requires-Dist: toolz
